lanfang/__init__.py
lanfang/dev/__init__.py
lanfang/network/__init__.py
lanfang/network/email.py
lanfang/network/netdata.py
lanfang/runner/__init__.py
lanfang/runner/__main__.py
lanfang/runner/base.py
lanfang/runner/cmd_runner.py
lanfang/runner/common.py
lanfang/runner/dependency.py
lanfang/runner/func_process_runner.py
lanfang/runner/multi_task_runner.py
lanfang/runner/proc_runner.py
lanfang/runner/progress.py
lanfang/runner/task_loader.py
lanfang/runner/task_register.py
lanfang/runner/task_runner.py
lanfang/utils/__init__.py
lanfang/utils/deprecation.py
lanfang/utils/disk.py
lanfang/utils/random.py
lanfang/utils/terminal.py
lanfang-0.1.5.dist-info/LICENSE
lanfang-0.1.5.dist-info/METADATA
lanfang-0.1.5.dist-info/WHEEL
lanfang-0.1.5.dist-info/top_level.txt
lanfang-0.1.5.dist-info/RECORD
